{
"type": "FeatureCollection",
"name": "LAJEADO DO BUGRE_Ordinaria_2012",
"crs": { "type": "name", "properties": { "name": "urn:ogc:def:crs:OGC:1.3:CRS84" } },
"features": [
{ "type": "Feature", "properties": { "SG_UF": "RS", "CD_MUNICIPIO": "86860", "NR_ZONA": "32", "NR_LOCAL_VOTACAO": "1031", "local_id": 746927, "ano": 2012, "sg_uf": "RS", "cd_localidade_tse": 86860, "cod_localidade_ibge": 4311429, "nr_locvot": 1031, "nr_cep": 98320000.0, "nm_localidade": "LAJEADO DO BUGRE", "nm_locvot": "ESCOLA ESTADUAL EUGENIO KORSACK", "ds_endereco": "SEDE DO MUNICIPIO", "ds_bairro": "CENTRO", "pred_long": -53.182412, "pred_lat": -27.690987, "pred_dist": 0.0195047314107035, "tse_long": null, "tse_lat": null, "long": -53.182412, "lat": -27.690987, "ID_UNICO": "LOC_071584", "NEI (PDT) (ELEITO) 1T": 531, "ROGELIO (PP) (NÃO ELEITO) 1T": 460, "Total_Votos_Validos 1T": 991, "Votos_Brancos 1T": 17, "Votos_Nulos 1T": 31, "Votos_Legenda 1T": 0, "Abstenções 1T": 65, "Eleitores_Aptos_Municipal 1T": 1104 }, "geometry": { "type": "Point", "coordinates": [ -53.182412, -27.690987 ] } },
{ "type": "Feature", "properties": { "SG_UF": "RS", "CD_MUNICIPIO": "86860", "NR_ZONA": "32", "NR_LOCAL_VOTACAO": "1066", "local_id": 746933, "ano": 2012, "sg_uf": "RS", "cd_localidade_tse": 86860, "cod_localidade_ibge": 4311429, "nr_locvot": 1066, "nr_cep": 98320000.0, "nm_localidade": "LAJEADO DO BUGRE", "nm_locvot": "EMATER", "ds_endereco": "CENTRO ADMINISTRATIVO", "ds_bairro": "CENTRO", "pred_long": -53.181699, "pred_lat": -27.690044, "pred_dist": 0.32620008279593798, "tse_long": null, "tse_lat": null, "long": -53.181699, "lat": -27.690044, "ID_UNICO": "LOC_071584", "NEI (PDT) (ELEITO) 1T": 302, "ROGELIO (PP) (NÃO ELEITO) 1T": 179, "Total_Votos_Validos 1T": 481, "Votos_Brancos 1T": 8, "Votos_Nulos 1T": 13, "Votos_Legenda 1T": 0, "Abstenções 1T": 24, "Eleitores_Aptos_Municipal 1T": 526 }, "geometry": { "type": "Point", "coordinates": [ -53.181699, -27.690044 ] } },
{ "type": "Feature", "properties": { "SG_UF": "RS", "CD_MUNICIPIO": "86860", "NR_ZONA": "32", "NR_LOCAL_VOTACAO": "1015", "local_id": 746940, "ano": 2012, "sg_uf": "RS", "cd_localidade_tse": 86860, "cod_localidade_ibge": 4311429, "nr_locvot": 1015, "nr_cep": 98320000.0, "nm_localidade": "LAJEADO DO BUGRE", "nm_locvot": "ESCOLA MUNICIPAL CARAMURU", "ds_endereco": "LINHA PICADA GRANDE", "ds_bairro": "CENTRO", "pred_long": -53.22075, "pred_lat": -27.71242, "pred_dist": 0.0282624897254866, "tse_long": null, "tse_lat": null, "long": -53.22075, "lat": -27.71242, "ID_UNICO": "LOC_071585", "NEI (PDT) (ELEITO) 1T": 194, "ROGELIO (PP) (NÃO ELEITO) 1T": 157, "Total_Votos_Validos 1T": 351, "Votos_Brancos 1T": 4, "Votos_Nulos 1T": 12, "Votos_Legenda 1T": 0, "Abstenções 1T": 27, "Eleitores_Aptos_Municipal 1T": 394 }, "geometry": { "type": "Point", "coordinates": [ -53.22075, -27.71242 ] } }
]
}
