{
"type": "FeatureCollection",
"name": "SANTA TEREZA_Ordinaria_2012",
"crs": { "type": "name", "properties": { "name": "urn:ogc:def:crs:OGC:1.3:CRS84" } },
"features": [
{ "type": "Feature", "properties": { "SG_UF": "RS", "CD_MUNICIPIO": "87629", "NR_ZONA": "8", "NR_LOCAL_VOTACAO": "1040", "local_id": 755710, "ano": 2012, "sg_uf": "RS", "cd_localidade_tse": 87629, "cod_localidade_ibge": 4317251, "nr_locvot": 1040, "nr_cep": 95715000.0, "nm_localidade": "SANTA TEREZA", "nm_locvot": "VICENTE RODRIGUES - ESCOLA", "ds_endereco": "RUA ELVESIO LISBOA, S/N", "ds_bairro": "CENTRO", "pred_long": -51.7367, "pred_lat": -29.16823, "pred_dist": 0.032705884180109501, "tse_long": null, "tse_lat": null, "long": -51.7367, "lat": -29.16823, "ID_UNICO": "LOC_072598", "DIOGO (PSDB) (ELEITO) 1T": 845, "RIBOLDI (PDT) (NÃO ELEITO) 1T": 519, "Total_Votos_Validos 1T": 1364, "Votos_Brancos 1T": 10, "Votos_Nulos 1T": 28, "Votos_Legenda 1T": 0, "Abstenções 1T": 52, "Eleitores_Aptos_Municipal 1T": 1454 }, "geometry": { "type": "Point", "coordinates": [ -51.7367, -29.16823 ] } },
{ "type": "Feature", "properties": { "SG_UF": "RS", "CD_MUNICIPIO": "87629", "NR_ZONA": "8", "NR_LOCAL_VOTACAO": "1023", "local_id": 755717, "ano": 2012, "sg_uf": "RS", "cd_localidade_tse": 87629, "cod_localidade_ibge": 4317251, "nr_locvot": 1023, "nr_cep": 95715000.0, "nm_localidade": "SANTA TEREZA", "nm_locvot": "AFONSO PENA - ESCOLA", "ds_endereco": "LINHA PEDERNEIRA", "ds_bairro": "SANTA TEREZA", "pred_long": -51.684718333333301, "pred_lat": -29.16651, "pred_dist": 0.41675386432146599, "tse_long": null, "tse_lat": null, "long": -51.684718333333301, "lat": -29.16651, "ID_UNICO": "LOC_072599", "DIOGO (PSDB) (ELEITO) 1T": 49, "RIBOLDI (PDT) (NÃO ELEITO) 1T": 36, "Total_Votos_Validos 1T": 85, "Votos_Brancos 1T": 0, "Votos_Nulos 1T": 2, "Votos_Legenda 1T": 0, "Abstenções 1T": 3, "Eleitores_Aptos_Municipal 1T": 90 }, "geometry": { "type": "Point", "coordinates": [ -51.684718333333301, -29.16651 ] } },
{ "type": "Feature", "properties": { "SG_UF": "RS", "CD_MUNICIPIO": "87629", "NR_ZONA": "8", "NR_LOCAL_VOTACAO": "1031", "local_id": 755724, "ano": 2012, "sg_uf": "RS", "cd_localidade_tse": 87629, "cod_localidade_ibge": 4317251, "nr_locvot": 1031, "nr_cep": 95715000.0, "nm_localidade": "SANTA TEREZA", "nm_locvot": "RODRIGUES ALVES - ESCOLA", "ds_endereco": "LINHA PRIMEIRA SECAO SANTA BARBARA", "ds_bairro": "SANTA TEREZA", "pred_long": -51.706427472222202, "pred_lat": -29.161633333333299, "pred_dist": 0.95050112700039802, "tse_long": null, "tse_lat": null, "long": -51.706427472222202, "lat": -29.161633333333299, "ID_UNICO": "LOC_072600", "DIOGO (PSDB) (ELEITO) 1T": 113, "RIBOLDI (PDT) (NÃO ELEITO) 1T": 79, "Total_Votos_Validos 1T": 192, "Votos_Brancos 1T": 1, "Votos_Nulos 1T": 4, "Votos_Legenda 1T": 0, "Abstenções 1T": 14, "Eleitores_Aptos_Municipal 1T": 211 }, "geometry": { "type": "Point", "coordinates": [ -51.706427472222202, -29.161633333333299 ] } }
]
}
