{
"type": "FeatureCollection",
"name": "SENADOR SALGADO FILHO_Ordinaria_2012",
"crs": { "type": "name", "properties": { "name": "urn:ogc:def:crs:OGC:1.3:CRS84" } },
"features": [
{ "type": "Feature", "properties": { "SG_UF": "RS", "CD_MUNICIPIO": "88765", "NR_ZONA": "127", "NR_LOCAL_VOTACAO": "1023", "local_id": 779332, "ano": 2012, "sg_uf": "RS", "cd_localidade_tse": 88765, "cod_localidade_ibge": 4320321, "nr_locvot": 1023, "nr_cep": 98895000.0, "nm_localidade": "SENADOR SALGADO FILHO", "nm_locvot": "ESCOLA ESTADUAL CARLOS GAKLIK", "ds_endereco": "RUA EVALDO KUPSKE, 93 - E", "ds_bairro": "CENTRO", "pred_long": -54.543164, "pred_lat": -28.028737, "pred_dist": 0.076194827147408203, "tse_long": null, "tse_lat": null, "long": -54.543164, "lat": -28.028737, "ID_UNICO": "LOC_074959", "HEICO SCHUUR (PP) (NÃO ELEITO) 1T": 605, "NORTON J. MATTER (PDT) (ELEITO) 1T": 751, "Total_Votos_Validos 1T": 1356, "Votos_Brancos 1T": 12, "Votos_Nulos 1T": 12, "Votos_Legenda 1T": 0, "Abstenções 1T": 79, "Eleitores_Aptos_Municipal 1T": 1459 }, "geometry": { "type": "Point", "coordinates": [ -54.543164, -28.028737 ] } },
{ "type": "Feature", "properties": { "SG_UF": "RS", "CD_MUNICIPIO": "88765", "NR_ZONA": "127", "NR_LOCAL_VOTACAO": "1015", "local_id": 779337, "ano": 2012, "sg_uf": "RS", "cd_localidade_tse": 88765, "cod_localidade_ibge": 4320321, "nr_locvot": 1015, "nr_cep": 98895000.0, "nm_localidade": "SENADOR SALGADO FILHO", "nm_locvot": "ESCOLA MUNUNICIPAL CRISTOVAO COLOMBO", "ds_endereco": "RINCAO MELGAREJO", "ds_bairro": "INTERIOR", "pred_long": -54.59197, "pred_lat": -27.98041, "pred_dist": 0.81707168648546002, "tse_long": null, "tse_lat": null, "long": -54.59197, "lat": -27.98041, "ID_UNICO": "LOC_074960", "HEICO SCHUUR (PP) (NÃO ELEITO) 1T": 99, "NORTON J. MATTER (PDT) (ELEITO) 1T": 113, "Total_Votos_Validos 1T": 212, "Votos_Brancos 1T": 0, "Votos_Nulos 1T": 1, "Votos_Legenda 1T": 0, "Abstenções 1T": 18, "Eleitores_Aptos_Municipal 1T": 231 }, "geometry": { "type": "Point", "coordinates": [ -54.59197, -27.98041 ] } },
{ "type": "Feature", "properties": { "SG_UF": "RS", "CD_MUNICIPIO": "88765", "NR_ZONA": "127", "NR_LOCAL_VOTACAO": "1058", "local_id": 779341, "ano": 2012, "sg_uf": "RS", "cd_localidade_tse": 88765, "cod_localidade_ibge": 4320321, "nr_locvot": 1058, "nr_cep": 98895000.0, "nm_localidade": "SENADOR SALGADO FILHO", "nm_locvot": "ESCOLA ESTADUAL SANTA MARIA", "ds_endereco": "LINHA GIRUAZINHO", "ds_bairro": "INTERIOR", "pred_long": -54.59197, "pred_lat": -27.98041, "pred_dist": 0.94455728699457597, "tse_long": null, "tse_lat": null, "long": -54.59197, "lat": -27.98041, "ID_UNICO": "LOC_074960", "HEICO SCHUUR (PP) (NÃO ELEITO) 1T": 101, "NORTON J. MATTER (PDT) (ELEITO) 1T": 128, "Total_Votos_Validos 1T": 229, "Votos_Brancos 1T": 2, "Votos_Nulos 1T": 3, "Votos_Legenda 1T": 0, "Abstenções 1T": 11, "Eleitores_Aptos_Municipal 1T": 245 }, "geometry": { "type": "Point", "coordinates": [ -54.59197, -27.98041 ] } },
{ "type": "Feature", "properties": { "SG_UF": "RS", "CD_MUNICIPIO": "88765", "NR_ZONA": "127", "NR_LOCAL_VOTACAO": "1040", "local_id": 779346, "ano": 2012, "sg_uf": "RS", "cd_localidade_tse": 88765, "cod_localidade_ibge": 4320321, "nr_locvot": 1040, "nr_cep": 98895000.0, "nm_localidade": "SENADOR SALGADO FILHO", "nm_locvot": "ESCOLA ESTADUAL FRANCISCO SALLES GUIMARAES", "ds_endereco": "RUA WILLY ALFREDO FEUERHARMEL", "ds_bairro": "DISTRITO DE 8 DE AGOSTO", "pred_long": -54.59197, "pred_lat": -27.98041, "pred_dist": 0.060977920135176403, "tse_long": null, "tse_lat": null, "long": -54.59197, "lat": -27.98041, "ID_UNICO": "LOC_074960", "HEICO SCHUUR (PP) (NÃO ELEITO) 1T": 197, "NORTON J. MATTER (PDT) (ELEITO) 1T": 131, "Total_Votos_Validos 1T": 328, "Votos_Brancos 1T": 0, "Votos_Nulos 1T": 2, "Votos_Legenda 1T": 0, "Abstenções 1T": 21, "Eleitores_Aptos_Municipal 1T": 351 }, "geometry": { "type": "Point", "coordinates": [ -54.59197, -27.98041 ] } },
{ "type": "Feature", "properties": { "SG_UF": "RS", "CD_MUNICIPIO": "88765", "NR_ZONA": "127", "NR_LOCAL_VOTACAO": "1074", "local_id": 779349, "ano": 2012, "sg_uf": "RS", "cd_localidade_tse": 88765, "cod_localidade_ibge": 4320321, "nr_locvot": 1074, "nr_cep": 98895000.0, "nm_localidade": "SENADOR SALGADO FILHO", "nm_locvot": "SALAO DA COMUNIDADE SANTO ANTONIO", "ds_endereco": "SEDE DISTRITAL", "ds_bairro": "DISTRITO DE ESQUINA IPIRANGA", "pred_long": -54.5244766666667, "pred_lat": -28.083721666666701, "pred_dist": 0.348223636382545, "tse_long": null, "tse_lat": null, "long": -54.5244766666667, "lat": -28.083721666666701, "ID_UNICO": "LOC_074962", "HEICO SCHUUR (PP) (NÃO ELEITO) 1T": 209, "NORTON J. MATTER (PDT) (ELEITO) 1T": 153, "Total_Votos_Validos 1T": 362, "Votos_Brancos 1T": 2, "Votos_Nulos 1T": 5, "Votos_Legenda 1T": 0, "Abstenções 1T": 25, "Eleitores_Aptos_Municipal 1T": 394 }, "geometry": { "type": "Point", "coordinates": [ -54.5244766666667, -28.083721666666701 ] } }
]
}
