{"type": "FeatureCollection", "features": [{"type": "Feature", "geometry": {"type": "Point", "coordinates": [-42.4042894, -22.0747749]}, "properties": {"local_id": 504831, "ano": 2000, "sg_uf": "RJ", "cd_localidade_tse": 58319, "cod_localidade_ibge": 3301603, "nr_zona": 53, "nr_locvot": 1040, "nr_cep": 28650000.0, "nm_localidade": "DUAS BARRAS", "nm_locvot": "CIEP 511 - PROF. ALAIDE ARAUJO STORCK MELLOR MARQUES", "ds_endereco": "RUA ANTONIO PEREIRA DA SILVA 123 - SEGUNDO DISTRITO", "ds_bairro": "MONNERAT", "pred_long": -42.4042894, "pred_lat": -22.0747749, "pred_dist": 0.0309004849191568, "tse_long": null, "tse_lat": null, "long": -42.4042894, "lat": -22.0747749, "ID_UNICO": "LOC_047247", "Antonio Carlos (PDT) (NÃO ELEITO) 1T": 972, "Mingo Calvo (PL) (NÃO ELEITO) 1T": 33, "Jorge Henrique De A. Fernandes (PFL) (ELEITO) 1T": 878, "NR_TURNO 1T": 1, "Total_Votos_Validos 1T": 1883, "Votos_Brancos 1T": 19, "Votos_Nulos 1T": 98}}, {"type": "Feature", "geometry": {"type": "Point", "coordinates": [-42.522896, -22.051075]}, "properties": {"local_id": 504819, "ano": 2000, "sg_uf": "RJ", "cd_localidade_tse": 58319, "cod_localidade_ibge": 3301603, "nr_zona": 53, "nr_locvot": 1023, "nr_cep": 28650000.0, "nm_localidade": "DUAS BARRAS", "nm_locvot": "ESCOLA ESTADUAL ALMIRANTE PROTOGENES", "ds_endereco": "AV. GETULIO VARGAS 104", "ds_bairro": "CENTRO", "pred_long": -42.522896, "pred_lat": -22.051075, "pred_dist": 0.0272441651552105, "tse_long": null, "tse_lat": null, "long": -42.522896, "lat": -22.051075, "ID_UNICO": "LOC_047245", "Antonio Carlos (PDT) (NÃO ELEITO) 1T": 1266, "Mingo Calvo (PL) (NÃO ELEITO) 1T": 119, "Jorge Henrique De A. Fernandes (PFL) (ELEITO) 1T": 1460, "NR_TURNO 1T": 1, "Total_Votos_Validos 1T": 2845, "Votos_Brancos 1T": 32, "Votos_Nulos 1T": 136}}, {"type": "Feature", "geometry": {"type": "Point", "coordinates": [-42.519395, -22.054739]}, "properties": {"local_id": 504825, "ano": 2000, "sg_uf": "RJ", "cd_localidade_tse": 58319, "cod_localidade_ibge": 3301603, "nr_zona": 53, "nr_locvot": 1031, "nr_cep": 28650000.0, "nm_localidade": "DUAS BARRAS", "nm_locvot": "ESCOLA MUNICIPAL EX-COMBATENTE AMANCIO PINTO", "ds_endereco": "RUA DR. FELICIANO SODRE S/N - BAU", "ds_bairro": "CENTRO", "pred_long": -42.519395, "pred_lat": -22.054739, "pred_dist": 0.0214633157415274, "tse_long": null, "tse_lat": null, "long": -42.519395, "lat": -22.054739, "ID_UNICO": "LOC_047246", "Antonio Carlos (PDT) (NÃO ELEITO) 1T": 539, "Mingo Calvo (PL) (NÃO ELEITO) 1T": 67, "Jorge Henrique De A. Fernandes (PFL) (ELEITO) 1T": 583, "NR_TURNO 1T": 1, "Total_Votos_Validos 1T": 1189, "Votos_Brancos 1T": 13, "Votos_Nulos 1T": 72}}, {"type": "Feature", "geometry": {"type": "Point", "coordinates": [-42.52267, -22.05127]}, "properties": {"local_id": 504813, "ano": 2000, "sg_uf": "RJ", "cd_localidade_tse": 58319, "cod_localidade_ibge": 3301603, "nr_zona": 53, "nr_locvot": 1015, "nr_cep": 28650000.0, "nm_localidade": "DUAS BARRAS", "nm_locvot": "CRECHE ESCOLA MUNICIPAL BERENICE SOARES SILVEIRA", "ds_endereco": "AV. GETULIO VARGAS 55", "ds_bairro": "CENTRO", "pred_long": -42.52267, "pred_lat": -22.05127, "pred_dist": 0.0201593882547051, "tse_long": null, "tse_lat": null, "long": -42.52267, "lat": -22.05127, "ID_UNICO": "LOC_047245", "Antonio Carlos (PDT) (NÃO ELEITO) 1T": 360, "Mingo Calvo (PL) (NÃO ELEITO) 1T": 57, "Jorge Henrique De A. Fernandes (PFL) (ELEITO) 1T": 424, "NR_TURNO 1T": 1, "Total_Votos_Validos 1T": 841, "Votos_Brancos 1T": 5, "Votos_Nulos 1T": 35}}]}