{"type": "FeatureCollection", "features": [{"type": "Feature", "geometry": {"type": "Point", "coordinates": [-41.871467, -20.926408]}, "properties": {"local_id": 498951, "ano": 2004, "sg_uf": "RJ", "cd_localidade_tse": 58084, "cod_localidade_ibge": 3306156, "nr_zona": 43, "nr_locvot": 1120, "nr_cep": 28375000.0, "nm_localidade": "VARRE E SAI", "nm_locvot": "CIEP DE VARRE-SAI", "ds_endereco": "RODOVIA MAURO ALVES RUBEIRO JUNIOR", "ds_bairro": "CENTRO", "pred_long": -41.871467, "pred_lat": -20.926408, "pred_dist": 0.046249758468582, "tse_long": null, "tse_lat": null, "long": -41.871467, "lat": -20.926408, "ID_UNICO": "LOC_046565", "Renda Media": 935.56, "Pct Branca": 68.68, "Pct Preta": 9.11, "Pct Parda": 21.85, "Pct Amarela": 0.35, "Pct Indigena": 0.0, "Pct Homens": 51.3, "Pct Mulheres": 48.7, "Pct 0 a 4 anos": 5.29, "Pct 5 a 9 anos": 4.17, "Pct 10 a 14 anos": 5.01, "Pct 15 a 19 anos": 4.84, "Pct 20 a 24 anos": 6.03, "Pct 25 a 29 anos": 5.12, "Pct 30 a 34 anos": 5.54, "Pct 35 a 39 anos": 4.77, "Pct 40 a 44 anos": 4.17, "Pct 45 a 49 anos": 4.24, "Pct 50 a 54 anos": 4.77, "Pct 55 a 59 anos": 4.45, "Pct 60 a 64 anos": 4.31, "Pct 65 a 69 anos": 5.29, "Pct 70 a 74 anos": 5.82, "Pct 75 a 79 anos": 5.85, "Pct 80 a 84 anos": 5.75, "Pct 85 a 89 anos": 5.19, "Pct 90 a 94 anos": 4.48, "Pct 95 a 99 anos": 4.94, "Pct Alfabetizados": 94.24, "Pct Esgoto Rede Geral": 94.62, "Pct Fossa Septica": 3.91, "Pct Esgoto Inadequado": 0.91, "Antonio Said (PMDB) (ELEITO) 1T": 1189, "Everardo (PP) (NÃO ELEITO) 1T": 1010, "Jairo Vieira (PV) (NÃO ELEITO) 1T": 21, "NR_TURNO 1T": 1, "Total_Votos_Validos 1T": 2220, "Votos_Brancos 1T": 17, "Votos_Nulos 1T": 132}}, {"type": "Feature", "geometry": {"type": "Point", "coordinates": [-41.74308, -20.857709]}, "properties": {"local_id": 498944, "ano": 2004, "sg_uf": "RJ", "cd_localidade_tse": 58084, "cod_localidade_ibge": 3306156, "nr_zona": 43, "nr_locvot": 1104, "nr_cep": 28375000.0, "nm_localidade": "VARRE E SAI", "nm_locvot": "ESCOLA ESTADUAL ELIDIO VALENTIM", "ds_endereco": "VILA DA PRATA S/N", "ds_bairro": "VILA DA PRATA", "pred_long": -41.74308, "pred_lat": -20.857709, "pred_dist": 0.0775894503650774, "tse_long": null, "tse_lat": null, "long": -41.74308, "lat": -20.857709, "ID_UNICO": "LOC_046564", "Renda Media": 644.51, "Pct Branca": 60.02, "Pct Preta": 13.95, "Pct Parda": 25.73, "Pct Amarela": 0.3, "Pct Indigena": 0.0, "Pct Homens": 54.84, "Pct Mulheres": 45.16, "Pct 0 a 4 anos": 4.16, "Pct 5 a 9 anos": 4.02, "Pct 10 a 14 anos": 5.33, "Pct 15 a 19 anos": 5.52, "Pct 20 a 24 anos": 5.83, "Pct 25 a 29 anos": 5.06, "Pct 30 a 34 anos": 5.29, "Pct 35 a 39 anos": 4.97, "Pct 40 a 44 anos": 5.88, "Pct 45 a 49 anos": 5.24, "Pct 50 a 54 anos": 5.56, "Pct 55 a 59 anos": 5.06, "Pct 60 a 64 anos": 4.66, "Pct 65 a 69 anos": 4.43, "Pct 70 a 74 anos": 4.97, "Pct 75 a 79 anos": 3.93, "Pct 80 a 84 anos": 5.61, "Pct 85 a 89 anos": 5.06, "Pct 90 a 94 anos": 4.48, "Pct 95 a 99 anos": 4.93, "Pct Alfabetizados": 81.32, "Pct Esgoto Rede Geral": 28.8, "Pct Fossa Septica": 2.56, "Pct Esgoto Inadequado": 68.46, "Antonio Said (PMDB) (ELEITO) 1T": 177, "Everardo (PP) (NÃO ELEITO) 1T": 98, "Jairo Vieira (PV) (NÃO ELEITO) 1T": 2, "NR_TURNO 1T": 1, "Total_Votos_Validos 1T": 277, "Votos_Brancos 1T": 6, "Votos_Nulos 1T": 17}}]}